odoo/addons/hr_department_code/README.rst
odoo/addons/hr_department_code/__init__.py
odoo/addons/hr_department_code/__manifest__.py
odoo/addons/hr_department_code/i18n/de.po
odoo/addons/hr_department_code/i18n/es.po
odoo/addons/hr_department_code/i18n/es_AR.po
odoo/addons/hr_department_code/i18n/hr.po
odoo/addons/hr_department_code/i18n/hr_department_code.pot
odoo/addons/hr_department_code/i18n/it.po
odoo/addons/hr_department_code/i18n/pt_BR.po
odoo/addons/hr_department_code/models/__init__.py
odoo/addons/hr_department_code/models/hr_department.py
odoo/addons/hr_department_code/readme/CONTRIBUTORS.rst
odoo/addons/hr_department_code/readme/DESCRIPTION.rst
odoo/addons/hr_department_code/static/description/icon.png
odoo/addons/hr_department_code/static/description/index.html
odoo/addons/hr_department_code/tests/__init__.py
odoo/addons/hr_department_code/tests/test_hr_department_code.py
odoo/addons/hr_department_code/views/hr_department_views.xml
odoo14_addon_hr_department_code-14.0.1.0.1.dev16.dist-info/METADATA
odoo14_addon_hr_department_code-14.0.1.0.1.dev16.dist-info/WHEEL
odoo14_addon_hr_department_code-14.0.1.0.1.dev16.dist-info/top_level.txt
odoo14_addon_hr_department_code-14.0.1.0.1.dev16.dist-info/RECORD
